Metadata-Version: 1.1
Name: pyslides
Version: 0.9.31
Summary: Python-based tool for presentation-ready slides
Home-page: UNKNOWN
Author: Giuseppe Romano
Author-email: romanog@mit.edu
License: GPLv2
Platform: UNKNOWN
Classifier: Programming Language :: Python :: 2.7
Classifier: Programming Language :: Python :: 3.6
